file_finder/cli.py
file_finder/constants.py
file_finder/exceptions.py
file_finder/finder.py
file_finder/utils.py
filehound-0.1.0.dist-info/METADATA
filehound-0.1.0.dist-info/WHEEL
filehound-0.1.0.dist-info/entry_points.txt
filehound-0.1.0.dist-info/RECORD
